gee_downloader/__init__.py
gee_downloader/gee_downloader.py
gee_downloader-0.0.1.dist-info/LICENSE
gee_downloader-0.0.1.dist-info/METADATA
gee_downloader-0.0.1.dist-info/WHEEL
gee_downloader-0.0.1.dist-info/top_level.txt
gee_downloader-0.0.1.dist-info/RECORD
