Metadata-Version: 2.1
Name: gee_downloader
Version: 0.0.1
Summary: Evoland models and data loaders
Author-email: Vytautas Jancauskas <vytautas.jancauskas@dlr.de>
Project-URL: Homepage, https://github.com/DLR-MF-DAS/gee_downloader
Project-URL: Issues, https://github.com/DLR-MF-DAS/gee_downloader/issues
Classifier: Programming Language :: Python :: 3
Classifier: License :: OSI Approved :: MIT License
Classifier: Operating System :: OS Independent
Requires-Python: >=3.8
License-File: LICENSE
Requires-Dist: geedim
Requires-Dist: rasterio
Requires-Dist: pytest
Requires-Dist: click
Requires-Dist: pdoc
